c64tools/charpacker.py
c64tools/charset2png.py
c64tools/filemerge.py
c64tools/mem2png.py
c64tools/structures.py
c64tools-0.20.0.dist-info/licenses/LICENSE
tests/ata_1.bin
tests/ata_1_1_1x1.png
tests/ata_1_2_1x2.png
tests/chr_out.bin
tests/mem1.png
tests/mem2.bin
tests/mem2_1.bin
tests/mem2_2.bin
tests/scr_out.bin
tests/test.hir.gif
tests/test_charpacker.py
tests/test_charset2png.py
tests/test_filemerge.py
tests/test_mem2png.py
tests/util.py
c64tools-0.20.0.dist-info/METADATA
c64tools-0.20.0.dist-info/WHEEL
c64tools-0.20.0.dist-info/entry_points.txt
c64tools-0.20.0.dist-info/top_level.txt
c64tools-0.20.0.dist-info/RECORD
