Metadata-Version: 2.4
Name: c64tools
Version: 0.20.0
Summary: c64 Python helper
Home-page: http://c64tools.readthedocs.org/
Download-URL: http://pypi.python.org/pypi/c64tools
Author: dkrajzew
Author-email: d.krajzewicz@gmail.com
License: BSD-3-Clause
Project-URL: Documentation, https://c64tools.readthedocs.io/
Project-URL: Source, https://github.com/dkrajzew/c64tools
Project-URL: Tracker, https://github.com/dkrajzew/c64tools/issues
Project-URL: Discussions, https://github.com/dkrajzew/c64tools/discussions
Classifier: Development Status :: 4 - Beta
Classifier: Environment :: Console
Classifier: Programming Language :: Python
Classifier: Programming Language :: Python :: 3
Classifier: Operating System :: OS Independent
Classifier: Intended Audience :: Other Audience
Classifier: Topic :: Artistic Software
Classifier: Topic :: Software Development :: Libraries :: Python Modules
Classifier: Topic :: Other/Nonlisted Topic
Classifier: Topic :: Multimedia :: Graphics
Requires-Python: >=3, <4
License-File: LICENSE
Requires-Dist: pygame==2.6.0
Dynamic: author
Dynamic: author-email
Dynamic: classifier
Dynamic: description
Dynamic: description-content-type
Dynamic: download-url
Dynamic: home-page
Dynamic: license
Dynamic: license-file
Dynamic: project-url
Dynamic: requires-dist
Dynamic: requires-python
Dynamic: summary
